{
  "miniprogramRoot": "miniprogram/",
  "cloudfunctionRoot": "cloudfunctions/",
  "setting": {
    "urlCheck": true,
    "es6": true,
    "enhance": true,
    "postcss": true,
    "preloadBackgroundData": false,
    "minified": true,
    "newFeature": true,
    "coverView": true,
    "nodeModules": false,
    "autoAudits": false,
    "showShadowRootInWxmlPanel": true,
    "scopeDataCheck": false,
    "uglifyFileName": false,
    "checkInvalidKey": true,
    "checkSiteMap": true,
    "uploadWithSourceMap": true,
    "compileHotReLoad": false,
    "useMultiFrameRuntime": false,
    "useApiHook": true,
    "babelSetting": {
      "ignore": [],
      "disablePlugins": [],
      "outputPath": ""
    },
    "useIsolateContext": true,
    "useCompilerModule": true,
    "userConfirmedUseCompilerModuleSwitch": false,
    "packNpmManually": false,
    "packNpmRelationList": []
  },
  "appid": "wxa8f600d5fc6f11e7",
  "projectname": "music-imooc",
  "libVersion": "2.8.1",
  "simulatorType": "wechat",
  "simulatorPluginLibVersion": {},
  "cloudfunctionTemplateRoot": "cloudfunctionTemplate",
  "condition": {
    "search": {
      "current": -1,
      "list": []
    },
    "conversation": {
      "current": -1,
      "list": []
    },
    "plugin": {
      "current": -1,
      "list": []
    },
    "game": {
      "list": []
    },
    "gamePlugin": {
      "current": -1,
      "list": []
    },
    "miniprogram": {
      "current": -1,
      "list": [
        {
          "id": -1,
          "name": "blog",
          "pathName": "pages/blog/blog",
          "query": "",
          "scene": null
        },
        {
          "id": 1,
          "name": "pages/blog/blog-edt",
          "pathName": "pages/blog-edit/blog-edit",
          "query": "nickName=Step.Up&avatarUrl=https://thirdwx.qlogo.cn/mmopen/vi_32/KiczNE4fwe0N76IJe8dSUHGTh0W8oJWll7g12bFNvI2QCydicsl769V3J0K8Jz6Bwed7dPVnYbWQGkRRiaicdHIfiaQ/132",
          "scene": null
        }
      ]
    }
  }
}